[{"__symbolic":"module","version":4,"metadata":{"KeychainTouchId":{"__symbolic":"class","extends":{"__symbolic":"reference","module":"@ionic-native/core","name":"IonicNativePlugin","line":33,"character":37},"decorators":[{"__symbolic":"call","expression":{"__symbolic":"reference","module":"@ionic-native/core","name":"Plugin","line":25,"character":1},"arguments":[{"pluginName":"KeychainTouchId","plugin":"cordova-plugin-keychain-touch-id","pluginRef":"plugins.touchid","repo":"https://github.com/sjhoeksma/cordova-plugin-keychain-touch-id","platforms":["Android","iOS"]}]},{"__symbolic":"call","expression":{"__symbolic":"reference","module":"@angular/core","name":"Injectable","line":32,"character":1}}],"members":{"isAvailable":[{"__symbolic":"method","decorators":[{"__symbolic":"call","expression":{"__symbolic":"reference","module":"@ionic-native/core","name":"Cordova","line":39,"character":3}}]}],"save":[{"__symbolic":"method","decorators":[{"__symbolic":"call","expression":{"__symbolic":"reference","module":"@ionic-native/core","name":"Cordova","line":51,"character":3}}]}],"verify":[{"__symbolic":"method","decorators":[{"__symbolic":"call","expression":{"__symbolic":"reference","module":"@ionic-native/core","name":"Cordova","line":61,"character":3}}]}],"has":[{"__symbolic":"method","decorators":[{"__symbolic":"call","expression":{"__symbolic":"reference","module":"@ionic-native/core","name":"Cordova","line":69,"character":3}}]}],"delete":[{"__symbolic":"method","decorators":[{"__symbolic":"call","expression":{"__symbolic":"reference","module":"@ionic-native/core","name":"Cordova","line":77,"character":3}}]}],"setLocale":[{"__symbolic":"method","decorators":[{"__symbolic":"call","expression":{"__symbolic":"reference","module":"@ionic-native/core","name":"Cordova","line":84,"character":3}}]}]}}}}]